entx/__init__.py
entx/errors.py
entx/storage.py
entx/users.py
entx/utils.py
entx-3.1.0.dist-info/METADATA
entx-3.1.0.dist-info/WHEEL
entx-3.1.0.dist-info/licenses/LICENSE
entx-3.1.0.dist-info/RECORD
