Metadata-Version: 2.1
Name: entx
Version: 3.1.0
Summary: The EntX encryption library for python.
Project-URL: Homepage, https://github.com/MaskdDev/entx
Project-URL: Bug Tracker, https://github.com/MaskdDev/entx/issues
Author-email: MaskdDev <maskddev@gmail.com>
License-File: LICENSE
Classifier: License :: OSI Approved :: MIT License
Classifier: Operating System :: OS Independent
Classifier: Programming Language :: Python :: 3
Requires-Python: >=3.10
